<?xml version="1.0" encoding="Windows-1252"?>
<ChunkGroupData xmlns:xsi="http://www.w3.org/2001/XMLSchema-instance" xmlns:xsd="http://www.w3.org/2001/XMLSchema">
  <chunks>
    <ArrayOfChunk>
      <Chunk>
        <State>UndiscoveredSea</State>
      </Chunk>
      <Chunk>
        <State>UndiscoveredSea</State>
      </Chunk>
      <Chunk>
        <State>UndiscoveredSea</State>
      </Chunk>
      <Chunk>
        <State>UndiscoveredSea</State>
      </Chunk>
      <Chunk>
        <State>UndiscoveredSea</State>
      </Chunk>
      <Chunk>
        <State>UndiscoveredSea</State>
      </Chunk>
      <Chunk>
        <State>UndiscoveredSea</State>
      </Chunk>
      <Chunk>
        <State>UndiscoveredSea</State>
      </Chunk>
      <Chunk>
        <State>UndiscoveredSea</State>
      </Chunk>
      <Chunk>
        <State>UndiscoveredSea</State>
      </Chunk>
    </ArrayOfChunk>
    <ArrayOfChunk>
      <Chunk>
        <State>UndiscoveredSea</State>
      </Chunk>
      <Chunk>
        <State>UndiscoveredSea</State>
      </Chunk>
      <Chunk>
        <State>UndiscoveredSea</State>
      </Chunk>
      <Chunk>
        <State>UndiscoveredIsland</State>
        <IslandData>
          <positionOnScreen>
            <x>432.670654</x>
            <y>306.145935</y>
          </positionOnScreen>
          <storyManager>
            <storyHandlers>
              <StoryHandler>
                <row>0</row>
                <col>0</col>
                <fallBackLayer>0</fallBackLayer>
                <storyID>8</storyID>
                <storyNameDebug>Hangar</storyNameDebug>
                <storyType>Normal</storyType>
                <contentDecals />
                <loots />
                <crews />
                <Crews />
              </StoryHandler>
            </storyHandlers>
          </storyManager>
        </IslandData>
      </Chunk>
      <Chunk>
        <State>UndiscoveredSea</State>
      </Chunk>
      <Chunk>
        <State>UndiscoveredSea</State>
      </Chunk>
      <Chunk>
        <State>UndiscoveredSea</State>
      </Chunk>
      <Chunk>
        <State>UndiscoveredSea</State>
      </Chunk>
      <Chunk>
        <State>UndiscoveredSea</State>
      </Chunk>
      <Chunk>
        <State>UndiscoveredSea</State>
      </Chunk>
    </ArrayOfChunk>
    <ArrayOfChunk>
      <Chunk>
        <State>UndiscoveredSea</State>
      </Chunk>
      <Chunk>
        <State>UndiscoveredSea</State>
      </Chunk>
      <Chunk>
        <State>UndiscoveredSea</State>
      </Chunk>
      <Chunk>
        <State>UndiscoveredSea</State>
      </Chunk>
      <Chunk>
        <State>UndiscoveredSea</State>
      </Chunk>
      <Chunk>
        <State>UndiscoveredSea</State>
      </Chunk>
      <Chunk>
        <State>UndiscoveredSea</State>
      </Chunk>
      <Chunk>
        <State>UndiscoveredSea</State>
      </Chunk>
      <Chunk>
        <State>UndiscoveredSea</State>
      </Chunk>
      <Chunk>
        <State>UndiscoveredSea</State>
      </Chunk>
    </ArrayOfChunk>
    <ArrayOfChunk>
      <Chunk>
        <State>UndiscoveredSea</State>
      </Chunk>
      <Chunk>
        <State>UndiscoveredSea</State>
      </Chunk>
      <Chunk>
        <State>UndiscoveredSea</State>
      </Chunk>
      <Chunk>
        <State>UndiscoveredSea</State>
      </Chunk>
      <Chunk>
        <State>UndiscoveredSea</State>
      </Chunk>
      <Chunk>
        <State>UndiscoveredSea</State>
      </Chunk>
      <Chunk>
        <State>UndiscoveredSea</State>
      </Chunk>
      <Chunk>
        <State>UndiscoveredSea</State>
      </Chunk>
      <Chunk>
        <State>UndiscoveredIsland</State>
        <IslandData>
          <positionOnScreen>
            <x>356.786316</x>
            <y>350.241852</y>
          </positionOnScreen>
          <storyManager>
            <storyHandlers>
              <StoryHandler>
                <row>0</row>
                <col>0</col>
                <fallBackLayer>0</fallBackLayer>
                <storyID>10</storyID>
                <storyNameDebug>Labyrinthe</storyNameDebug>
                <storyType>Normal</storyType>
                <contentDecals />
                <loots />
                <crews />
                <Crews />
              </StoryHandler>
            </storyHandlers>
          </storyManager>
        </IslandData>
      </Chunk>
      <Chunk>
        <State>UndiscoveredSea</State>
      </Chunk>
    </ArrayOfChunk>
    <ArrayOfChunk>
      <Chunk>
        <State>UndiscoveredSea</State>
      </Chunk>
      <Chunk>
        <State>UndiscoveredSea</State>
      </Chunk>
      <Chunk>
        <State>UndiscoveredSea</State>
      </Chunk>
      <Chunk>
        <State>UndiscoveredIsland</State>
        <IslandData>
          <positionOnScreen>
            <x>324.574066</x>
            <y>330.66684</y>
          </positionOnScreen>
          <storyManager>
            <storyHandlers>
              <StoryHandler>
                <row>0</row>
                <col>0</col>
                <fallBackLayer>0</fallBackLayer>
                <storyID>16</storyID>
                <storyNameDebug>Marchand d? choses</storyNameDebug>
                <storyType>Normal</storyType>
                <contentDecals />
                <loots />
                <crews />
                <Crews />
              </StoryHandler>
            </storyHandlers>
          </storyManager>
        </IslandData>
      </Chunk>
      <Chunk>
        <State>UndiscoveredSea</State>
      </Chunk>
      <Chunk>
        <State>UndiscoveredSea</State>
      </Chunk>
      <Chunk>
        <State>UndiscoveredSea</State>
      </Chunk>
      <Chunk>
        <State>UndiscoveredSea</State>
      </Chunk>
      <Chunk>
        <State>UndiscoveredSea</State>
      </Chunk>
      <Chunk>
        <State>UndiscoveredSea</State>
      </Chunk>
    </ArrayOfChunk>
    <ArrayOfChunk>
      <Chunk>
        <State>UndiscoveredSea</State>
      </Chunk>
      <Chunk>
        <State>UndiscoveredSea</State>
      </Chunk>
      <Chunk>
        <State>UndiscoveredSea</State>
      </Chunk>
      <Chunk>
        <State>UndiscoveredSea</State>
      </Chunk>
      <Chunk>
        <State>UndiscoveredIsland</State>
        <IslandData>
          <positionOnScreen>
            <x>378.272858</x>
            <y>87.07063</y>
          </positionOnScreen>
          <storyManager>
            <storyHandlers>
              <StoryHandler>
                <row>0</row>
                <col>0</col>
                <fallBackLayer>0</fallBackLayer>
                <storyID>4</storyID>
                <storyNameDebug>Epave</storyNameDebug>
                <storyType>Normal</storyType>
                <contentDecals />
                <loots />
                <crews />
                <Crews />
              </StoryHandler>
            </storyHandlers>
          </storyManager>
        </IslandData>
      </Chunk>
      <Chunk>
        <State>UndiscoveredSea</State>
      </Chunk>
      <Chunk>
        <State>UndiscoveredSea</State>
      </Chunk>
      <Chunk>
        <State>UndiscoveredIsland</State>
        <IslandData>
          <positionOnScreen>
            <x>288.186829</x>
            <y>359.549042</y>
          </positionOnScreen>
          <storyManager>
            <storyHandlers>
              <StoryHandler>
                <row>0</row>
                <col>0</col>
                <fallBackLayer>0</fallBackLayer>
                <storyID>9</storyID>
                <storyNameDebug>Île Déserte</storyNameDebug>
                <storyType>Normal</storyType>
                <contentDecals />
                <loots />
                <crews />
                <Crews />
              </StoryHandler>
            </storyHandlers>
          </storyManager>
        </IslandData>
      </Chunk>
      <Chunk>
        <State>UndiscoveredSea</State>
      </Chunk>
      <Chunk>
        <State>UndiscoveredSea</State>
      </Chunk>
    </ArrayOfChunk>
    <ArrayOfChunk>
      <Chunk>
        <State>UndiscoveredSea</State>
      </Chunk>
      <Chunk>
        <State>UndiscoveredSea</State>
      </Chunk>
      <Chunk>
        <State>UndiscoveredSea</State>
      </Chunk>
      <Chunk>
        <State>UndiscoveredSea</State>
      </Chunk>
      <Chunk>
        <State>UndiscoveredSea</State>
      </Chunk>
      <Chunk>
        <State>UndiscoveredSea</State>
      </Chunk>
      <Chunk>
        <State>UndiscoveredSea</State>
      </Chunk>
      <Chunk>
        <State>UndiscoveredSea</State>
      </Chunk>
      <Chunk>
        <State>UndiscoveredSea</State>
      </Chunk>
      <Chunk>
        <State>UndiscoveredSea</State>
      </Chunk>
    </ArrayOfChunk>
    <ArrayOfChunk>
      <Chunk>
        <State>UndiscoveredSea</State>
      </Chunk>
      <Chunk>
        <State>UndiscoveredSea</State>
      </Chunk>
      <Chunk>
        <State>UndiscoveredSea</State>
      </Chunk>
      <Chunk>
        <State>UndiscoveredSea</State>
      </Chunk>
      <Chunk>
        <State>UndiscoveredSea</State>
      </Chunk>
      <Chunk>
        <State>UndiscoveredSea</State>
      </Chunk>
      <Chunk>
        <State>UndiscoveredSea</State>
      </Chunk>
      <Chunk>
        <State>UndiscoveredSea</State>
      </Chunk>
      <Chunk>
        <State>UndiscoveredSea</State>
      </Chunk>
      <Chunk>
        <State>UndiscoveredSea</State>
      </Chunk>
    </ArrayOfChunk>
    <ArrayOfChunk>
      <Chunk>
        <State>UndiscoveredSea</State>
      </Chunk>
      <Chunk>
        <State>UndiscoveredSea</State>
      </Chunk>
      <Chunk>
        <State>UndiscoveredSea</State>
      </Chunk>
      <Chunk>
        <State>UndiscoveredSea</State>
      </Chunk>
      <Chunk>
        <State>UndiscoveredIsland</State>
        <IslandData>
          <positionOnScreen>
            <x>310.392151</x>
            <y>177.601135</y>
          </positionOnScreen>
          <storyManager>
            <storyHandlers>
              <StoryHandler>
                <row>0</row>
                <col>0</col>
                <fallBackLayer>0</fallBackLayer>
                <storyID>14</storyID>
                <storyNameDebug>Marchand de vêtements</storyNameDebug>
                <storyType>Normal</storyType>
                <contentDecals />
                <loots />
                <crews />
                <Crews />
              </StoryHandler>
            </storyHandlers>
          </storyManager>
        </IslandData>
      </Chunk>
      <Chunk>
        <State>UndiscoveredSea</State>
      </Chunk>
      <Chunk>
        <State>UndiscoveredIsland</State>
        <IslandData>
          <positionOnScreen>
            <x>356.803162</x>
            <y>270.972565</y>
          </positionOnScreen>
          <storyManager>
            <storyHandlers>
              <StoryHandler>
                <row>0</row>
                <col>0</col>
                <fallBackLayer>0</fallBackLayer>
                <storyID>10</storyID>
                <storyNameDebug>Labyrinthe</storyNameDebug>
                <storyType>Normal</storyType>
                <contentDecals />
                <loots />
                <crews />
                <Crews />
              </StoryHandler>
            </storyHandlers>
          </storyManager>
        </IslandData>
      </Chunk>
      <Chunk>
        <State>UndiscoveredSea</State>
      </Chunk>
      <Chunk>
        <State>UndiscoveredSea</State>
      </Chunk>
      <Chunk>
        <State>UndiscoveredSea</State>
      </Chunk>
    </ArrayOfChunk>
    <ArrayOfChunk>
      <Chunk>
        <State>UndiscoveredSea</State>
      </Chunk>
      <Chunk>
        <State>UndiscoveredSea</State>
      </Chunk>
      <Chunk>
        <State>UndiscoveredSea</State>
      </Chunk>
      <Chunk>
        <State>UndiscoveredSea</State>
      </Chunk>
      <Chunk>
        <State>UndiscoveredSea</State>
      </Chunk>
      <Chunk>
        <State>UndiscoveredSea</State>
      </Chunk>
      <Chunk>
        <State>UndiscoveredSea</State>
      </Chunk>
      <Chunk>
        <State>UndiscoveredSea</State>
      </Chunk>
      <Chunk>
        <State>UndiscoveredSea</State>
      </Chunk>
      <Chunk>
        <State>UndiscoveredSea</State>
      </Chunk>
    </ArrayOfChunk>
  </chunks>
</ChunkGroupData>